sklearnFunctions/__init__.py
sklearnFunctions/preprocessing.py
sklearnFunctions-0.0.9.dist-info/LICENSE
sklearnFunctions-0.0.9.dist-info/METADATA
sklearnFunctions-0.0.9.dist-info/WHEEL
sklearnFunctions-0.0.9.dist-info/top_level.txt
sklearnFunctions-0.0.9.dist-info/RECORD
