Metadata-Version: 2.1
Name: sklearnFunctions
Version: 0.0.9
Summary: module built on needy sklearn preprocessing functions
Home-page: https://github.com/Karthik-VG/sklearnFunctions
Author: Karthik-VG
Author-email: karthikvg.engineer@gmail.com
License: UNKNOWN
Project-URL: Bug Tracker, https://github.com/{USER_NAME}/{PROJECT_NAME}/issues
Platform: UNKNOWN
Classifier: Programming Language :: Python :: 3
Classifier: License :: OSI Approved :: MIT License
Classifier: Operating System :: OS Independent
Requires-Python: >=3.6
License-File: LICENSE
Requires-Dist: sklearn
Requires-Dist: pandas
Requires-Dist: numpy
